host_image_backup/__init__.py
host_image_backup/cli.py
host_image_backup/config/__init__.py
host_image_backup/config/config_manager.py
host_image_backup/config/config_models.py
host_image_backup/config/styles.py
host_image_backup/core/__init__.py
host_image_backup/core/backup.py
host_image_backup/core/service.py
host_image_backup/core/upload.py
host_image_backup/providers/__init__.py
host_image_backup/providers/base.py
host_image_backup/providers/cos.py
host_image_backup/providers/github.py
host_image_backup/providers/imgur.py
host_image_backup/providers/oss.py
host_image_backup/providers/provider_manager.py
host_image_backup/providers/sms.py
host_image_backup/utils/__init__.py
host_image_backup/utils/compression.py
host_image_backup/utils/exceptions.py
host_image_backup/utils/file_utils.py
host_image_backup/utils/metadata.py
host_image_backup-0.1.3.dist-info/METADATA
host_image_backup-0.1.3.dist-info/WHEEL
host_image_backup-0.1.3.dist-info/entry_points.txt
host_image_backup-0.1.3.dist-info/licenses/LICENSE
host_image_backup-0.1.3.dist-info/RECORD
