Metadata-Version: 2.4
Name: host-image-backup
Version: 0.1.3
Summary: A Python-based command-line tool for backing up images from multiple image hosting services to local storage
Project-URL: Homepage, https://waynexucn.github.io/app/HostImageBackup/index.html
Project-URL: Repository, https://github.com/WayneXuCN/HostImageBackup
Project-URL: Issues, https://github.com/WayneXuCN/HostImageBackup/issues
Author-email: Wenjie Xu <wenjie.xu.cn@outlook.com>
License: MIT
License-File: LICENSE
Keywords: CLI,backup,host,image,oss
Classifier: Development Status :: 4 - Beta
Classifier: Environment :: Console
Classifier: Intended Audience :: Developers
Classifier: License :: OSI Approved :: MIT License
Classifier: Operating System :: OS Independent
Classifier: Programming Language :: Python :: 3
Classifier: Programming Language :: Python :: 3.10
Classifier: Programming Language :: Python :: 3.11
Classifier: Programming Language :: Python :: 3.12
Classifier: Topic :: Utilities
Requires-Python: >=3.10
Requires-Dist: cos-python-sdk-v5
Requires-Dist: loguru
Requires-Dist: oss2
Requires-Dist: pillow
Requires-Dist: pydantic
Requires-Dist: python-dotenv
Requires-Dist: pyyaml
Requires-Dist: requests
Requires-Dist: rich
Requires-Dist: tqdm
Requires-Dist: typer
Provides-Extra: dev
Requires-Dist: black; extra == 'dev'
Requires-Dist: flake8; extra == 'dev'
Requires-Dist: mypy; extra == 'dev'
Requires-Dist: pre-commit; extra == 'dev'
Requires-Dist: pytest; extra == 'dev'
Requires-Dist: pytest-cov; extra == 'dev'
Requires-Dist: ruff; extra == 'dev'
